snapml/BatchedTreeEnsemble.py
snapml/BoostingMachine.py
snapml/BoostingMachineClassifier.py
snapml/BoostingMachineCommon.py
snapml/BoostingMachineRegressor.py
snapml/CommonModel.py
snapml/DecisionTree.py
snapml/DecisionTreeClassifier.py
snapml/DecisionTreeRegressor.py
snapml/GeneralizedLinearModel.py
snapml/GeneralizedLinearModelClassifier.py
snapml/GeneralizedLinearModelRegressor.py
snapml/GraphFeaturePreprocessor.py
snapml/LinearRegression.py
snapml/Loaders.py
snapml/LogisticRegression.py
snapml/MPI.py
snapml/Model.py
snapml/MultiOutputCalibratedClassifier.py
snapml/Partition.py
snapml/RBFSampler.py
snapml/RandomForest.py
snapml/RandomForestClassifier.py
snapml/RandomForestRegressor.py
snapml/SupportVectorMachine.py
snapml/Writers.py
snapml/__init__.py
snapml/_gpu_utils.py
snapml/_import.py
snapml/_predict_utils.py
snapml/io.py
snapml/libsnapmlcore.so
snapml/libsnapmlcore_avx2.so
snapml/libsnapmllocal3.so
snapml/libsnapmllocal3_avx2.so
snapml/libsnapmlutils.so
snapml/libsnapmlutils_avx2.so
snapml/main.md
snapml/metrics.py
snapml/model_io.py
snapml/pipeline_io.py
snapml/utils.py
snapml/version.py
snapml/docs/class-diagram-CommonModel.pdf
snapml/docs/class-diagram-CommonModel.pptx
snapml/docs/class-diagram-GeneralizedLinearModel.pdf
snapml/docs/class-diagram-GeneralizedLinearModel.pptx
snapml/include/AnyDataset.hpp
snapml/include/BoosterBuilder.hpp
snapml/include/BoosterModel.hpp
snapml/include/BoosterParams.hpp
snapml/include/BoosterPredictor.hpp
snapml/include/DataSchema.hpp
snapml/include/DecisionTreeBuilder.hpp
snapml/include/DecisionTreeModel.hpp
snapml/include/DecisionTreeParams.hpp
snapml/include/DecisionTreePredictor.hpp
snapml/include/DenseDataset.hpp
snapml/include/FunctionTransformer.hpp
snapml/include/GenericTreeEnsembleModel.hpp
snapml/include/GenericTreeEnsemblePredictor.hpp
snapml/include/GfpEncoder.hpp
snapml/include/KBinsDiscretizer.hpp
snapml/include/Normalizer.hpp
snapml/include/OneHotEncoder.hpp
snapml/include/OrdinalEncoder.hpp
snapml-1.17.1.dist-info/licenses/LICENSE.pdf
snapml-1.17.1.dist-info/METADATA
snapml-1.17.1.dist-info/WHEEL
snapml-1.17.1.dist-info/top_level.txt
snapml-1.17.1.dist-info/RECORD
