Metadata-Version: 2.4
Name: snapml
Version: 1.17.1
Summary: Snap Machine Learning
Author-email: IBM <tpa@zurich.ibm.com>
License: Proprietary
Project-URL: Homepage, https://www.zurich.ibm.com/snapml/
Classifier: Development Status :: 5 - Production/Stable
Classifier: Programming Language :: Python :: 3.9
Classifier: Programming Language :: Python :: 3.10
Classifier: Programming Language :: Python :: 3.11
Classifier: Programming Language :: Python :: 3.12
Classifier: Operating System :: Microsoft :: Windows :: Windows 10
Classifier: Operating System :: MacOS :: MacOS X
Classifier: Operating System :: POSIX :: Linux
Classifier: Intended Audience :: Science/Research
Classifier: Intended Audience :: Developers
Classifier: Intended Audience :: Information Technology
Classifier: License :: Other/Proprietary License
Classifier: Topic :: Software Development :: Libraries
Classifier: Topic :: Software Development :: Libraries :: Python Modules
Classifier: Topic :: Scientific/Engineering :: Artificial Intelligence
Requires-Python: >=3.9
License-File: LICENSE.pdf
Requires-Dist: scikit-learn
Requires-Dist: scipy
Requires-Dist: numpy
Dynamic: license-file
